eslite_movie/__init__.py
eslite_movie/cli.py
eslite_movie/const.py
eslite_movie/crawler.py
eslite_movie/main.py
eslite_movie-1.0.2.dist-info/LICENSE
eslite_movie-1.0.2.dist-info/METADATA
eslite_movie-1.0.2.dist-info/WHEEL
eslite_movie-1.0.2.dist-info/entry_points.txt
eslite_movie-1.0.2.dist-info/top_level.txt
eslite_movie-1.0.2.dist-info/RECORD
