Metadata-Version: 2.1
Name: eslite-movie
Version: 1.0.2
Summary: eslite movie crawler
Home-page: https://github.com/CliffLin/eslite-movie
Author: Cliff Lin
Author-email: zylintw@gmail.com
License: UNKNOWN
Platform: UNKNOWN
Classifier: Programming Language :: Python :: 3
Classifier: License :: OSI Approved :: MIT License
Classifier: Operating System :: OS Independent
Requires-Python: >=3.6
Requires-Dist: beautifulsoup4 (==4.6.3)
Requires-Dist: requests (==2.22.0)
Requires-Dist: rich (==9.5.1)
